VkApiBot/__init__.py
VkApiBot/utils/WorkerThread.py
VkApiBot/utils/backend_handlers.py
VkApiBot-1.0.4.dist-info/LICENSE
VkApiBot-1.0.4.dist-info/METADATA
VkApiBot-1.0.4.dist-info/WHEEL
VkApiBot-1.0.4.dist-info/top_level.txt
VkApiBot-1.0.4.dist-info/RECORD
