Metadata-Version: 2.1
Name: VkApiBot
Version: 1.0.4
Summary: Very well python library for easy work with vk_api lib.
Home-page: UNKNOWN
Author: Sicquze
Author-email: Sicquzeeee@gmail.com
License: UNKNOWN
Platform: UNKNOWN
Classifier: Programming Language :: Python :: 3.8
Classifier: License :: OSI Approved :: MIT License
Classifier: Operating System :: OS Independent
Requires-Python: >=3.8
